README.md
setup.py
calculator/__init__.py
calculator/calculator.py
calpython.egg-info/PKG-INFO
calpython.egg-info/SOURCES.txt
calpython.egg-info/dependency_links.txt
calpython.egg-info/top_level.txt