Metadata-Version: 2.1
Name: calpython
Version: 0.0.2
Summary: Calculator package for simple arithmetic operations.
Home-page: https://github.com/fortune-uwha/tc_calculator
Author: Fortune Uwha
Author-email: fortune.uwha@gmail.com
License: MIT
Download-URL: https://github.com/fortune-uwha/tc_calculator/archive/refs/tags/v0.0.2.tar.gz
Keywords: calculator,maths,arithmetic
Platform: UNKNOWN
Classifier: License :: OSI Approved :: MIT License
Classifier: Programming Language :: Python :: 3.6
Classifier: Programming Language :: Python :: 3.7
Classifier: Programming Language :: Python :: 3.8
Requires-Python: >=3.6
